matmech/__init__.py
matmech/axial_analysis.py
matmech/common_utils.py
matmech/config_defaults.py
matmech/constants.py
matmech/plotting_tools.py
matmech/torsional_analysis.py
matmech/workflow.py
matmech-1.0.6.dist-info/licenses/LICENSE
matmech-1.0.6.dist-info/METADATA
matmech-1.0.6.dist-info/WHEEL
matmech-1.0.6.dist-info/top_level.txt
matmech-1.0.6.dist-info/RECORD
