Metadata-Version: 2.4
Name: matmech
Version: 1.0.6
Summary: A library for analyzing data from universal test machines.
Author-email: Mitchell Blaha <mitchell@blahafamily.com>
License-Expression: MIT
Project-URL: Repository, https://github.com/WhiteRabbit2006/matmech
Classifier: Programming Language :: Python :: 3
Classifier: Operating System :: OS Independent
Classifier: Intended Audience :: Science/Research
Classifier: Topic :: Scientific/Engineering
Classifier: Topic :: Software Development :: Libraries :: Python Modules
Requires-Python: >=3.8
License-File: LICENSE
Requires-Dist: pandas
Requires-Dist: numpy
Requires-Dist: matplotlib
Provides-Extra: animation
Requires-Dist: imageio; extra == "animation"
Requires-Dist: imageio-ffmpeg; extra == "animation"
Provides-Extra: dev
Requires-Dist: pytest; extra == "dev"
Dynamic: license-file
